SoulsSaveCLI/__init__.py
SoulsSaveCLI/soulsave/__init__.py
SoulsSaveCLI/soulsave/core.py
SoulsSaveCLI/soulsave/soulsave.py
SoulsSaveCLI/utils/__init__.py
SoulsSaveCLI/utils/callbacks.py
SoulsSaveCLI/utils/side_functions.py
soulsave_cli-0.1.5.dist-info/LICENSE
soulsave_cli-0.1.5.dist-info/METADATA
soulsave_cli-0.1.5.dist-info/WHEEL
soulsave_cli-0.1.5.dist-info/entry_points.txt
soulsave_cli-0.1.5.dist-info/top_level.txt
soulsave_cli-0.1.5.dist-info/RECORD
