Metadata-Version: 2.2
Name: soulsave-cli
Version: 0.1.5
Home-page: https://github.com/silocone141/SoulsSaveCLI
Author: silocone
License: MIT
License-File: LICENSE
Requires-Dist: Click
Requires-Dist: setuptools
Requires-Dist: pyyaml
Provides-Extra: dev
Requires-Dist: twine; extra == "dev"
Dynamic: author
Dynamic: description
Dynamic: description-content-type
Dynamic: home-page
Dynamic: license
Dynamic: provides-extra
Dynamic: requires-dist
